fourpoints/__init__.py
fourpoints/analytics.py
fourpoints/api.py
fourpoints/gemini_client.py
fourpoints/location.py
fourpoints/obd_client.py
fourpoints/reports.py
fourpoints/streaming.py
fourpoints-0.1.7.dist-info/licenses/LICENSE
fourpoints-0.1.7.dist-info/METADATA
fourpoints-0.1.7.dist-info/WHEEL
fourpoints-0.1.7.dist-info/top_level.txt
fourpoints-0.1.7.dist-info/RECORD
