Metadata-Version: 2.4
Name: fourpoints
Version: 0.1.7
Summary: A production-grade Python library for real-time vehicle telemetry and diagnostics
Home-page: https://github.com/amrittmishra/fourpoints
Author: FourPoints Team
Author-email: FourPoints Team <info@fourpoints.example.com>
License: MIT
Project-URL: Homepage, https://github.com/fourpoints/fourpoints
Project-URL: Bug Tracker, https://github.com/fourpoints/fourpoints/issues
Project-URL: Documentation, https://fourpoints.readthedocs.io/
Keywords: obd,vehicle,telemetry,diagnostics,automotive
Classifier: Development Status :: 4 - Beta
Classifier: Intended Audience :: Developers
Classifier: License :: OSI Approved :: MIT License
Classifier: Programming Language :: Python :: 3
Classifier: Programming Language :: Python :: 3.8
Classifier: Programming Language :: Python :: 3.9
Classifier: Programming Language :: Python :: 3.10
Classifier: Programming Language :: Python :: 3.11
Classifier: Topic :: Software Development :: Libraries
Classifier: Topic :: System :: Hardware :: Hardware Drivers
Classifier: Topic :: Scientific/Engineering :: Information Analysis
Requires-Python: >=3.8
License-File: LICENSE
Requires-Dist: obd>=0.7.1
Requires-Dist: fastapi>=0.95.0
Requires-Dist: uvicorn>=0.21.1
Requires-Dist: pydantic>=1.10.7
Requires-Dist: google-generativeai==0.1.0rc1
Requires-Dist: jinja2>=3.1.2
Requires-Dist: weasyprint>=59.0
Requires-Dist: matplotlib>=3.7.1
Requires-Dist: gpsd-py3>=0.3.0
Requires-Dist: pyserial>=3.5
Requires-Dist: websockets>=11.0.3
Provides-Extra: dev
Requires-Dist: pytest>=7.3.1; extra == "dev"
Requires-Dist: pytest-asyncio>=0.21.0; extra == "dev"
Requires-Dist: black>=23.3.0; extra == "dev"
Requires-Dist: isort>=5.12.0; extra == "dev"
Requires-Dist: flake8>=6.0.0; extra == "dev"
Requires-Dist: mypy>=1.3.0; extra == "dev"
Provides-Extra: docs
Requires-Dist: sphinx>=6.2.1; extra == "docs"
Requires-Dist: sphinx-rtd-theme>=1.2.1; extra == "docs"
Dynamic: author
Dynamic: home-page
Dynamic: license-file
Dynamic: requires-python
